stabiliser_tools-1.0.8.data/purelib/stab_tools/__init__.py
stabiliser_tools-1.0.8.data/purelib/stab_tools/_stab_tools.cpython-38-darwin.so
stabiliser_tools-1.0.8.data/purelib/stab_tools/libfast_stabiliser.dylib
stabiliser_tools-1.0.8.dist-info/METADATA
stabiliser_tools-1.0.8.dist-info/WHEEL
stabiliser_tools-1.0.8.dist-info/top_level.txt
stabiliser_tools-1.0.8.dist-info/RECORD
