Metadata-Version: 2.1
Name: stabiliser-tools
Version: 1.0.8
Summary: Fast algorithms for verifying and converting specifications of stabiliser states and Clifford gates.
Author: Wilfred Salmon, Nadish de Silva, Ming Yin
Project-URL: Homepage, https://github.com/ndesilva/stabiliser-tools
Classifier: License :: OSI Approved :: GNU General Public License v3 (GPLv3)
Classifier: Programming Language :: Python
Classifier: Programming Language :: Python :: 3
Requires-Python: >=3.8
